<travelAgencies>
    <travelAgencyEntity>
        <name>Sunshine Travels</name>
        <city>Warszawa</city>
        <phoneNumber>+48 123 456 789</phoneNumber>
    </travelAgencyEntity>
    <travelAgencyEntity>
        <name>Adventure Seekers</name>
        <city>Kraków</city>
        <phoneNumber>+48 987 654 321</phoneNumber>
    </travelAgencyEntity>
    <travelAgencyEntity>
        <name>Relaxation Retreats</name>
        <city>Gdańsk</city>
        <phoneNumber>+48 564 738 290</phoneNumber>
    </travelAgencyEntity>
</travelAgencies>
